{
    "data": {
        "id": "bitcoin",
        "rank": "1",
        "symbol": "BTC",
        "name": "Bitcoin",
        "supply": "19545775.0000000000000000",
        "maxSupply": "21000000.0000000000000000",
        "marketCapUsd": "717094797957.7002162426956850",
        "volumeUsd24Hr": "3256404824.4131176157315797",
        "priceUsd": "36687.96",
        "changePercent24Hr": "0.4701416676592419",
        "vwap24Hr": "36584.7077749348715956",
        "explorer": "https://blockchain.info/"
    },
    "timestamp": 1700330294184
}